AU_atomicunit/__init__.py
AU_atomicunit/atomic_to_si.py
AU_atomicunit/si_to_atomic.py
AU_atomicunit-0.0.1.dist-info/METADATA
AU_atomicunit-0.0.1.dist-info/WHEEL
AU_atomicunit-0.0.1.dist-info/top_level.txt
AU_atomicunit-0.0.1.dist-info/RECORD
